README.rst
leavesdew.zip
screenshot.png
setup.py
docs/HISTORY.txt
docs/INSTALL.txt
docs/LICENSE.GPL
docs/LICENSE.txt
plonetheme/__init__.py
plonetheme.leavesdew.egg-info/PKG-INFO
plonetheme.leavesdew.egg-info/SOURCES.txt
plonetheme.leavesdew.egg-info/dependency_links.txt
plonetheme.leavesdew.egg-info/entry_points.txt
plonetheme.leavesdew.egg-info/namespace_packages.txt
plonetheme.leavesdew.egg-info/requires.txt
plonetheme.leavesdew.egg-info/top_level.txt
plonetheme/leavesdew/__init__.py
plonetheme/leavesdew/configure.zcml
plonetheme/leavesdew/profiles/default/metadata.xml
plonetheme/leavesdew/profiles/default/theme.xml
plonetheme/leavesdew/static/index.html
plonetheme/leavesdew/static/license.txt
plonetheme/leavesdew/static/manifest.cfg
plonetheme/leavesdew/static/plone-integration.css
plonetheme/leavesdew/static/rules.xml
plonetheme/leavesdew/static/style.css
plonetheme/leavesdew/static/images/img01.jpg
plonetheme/leavesdew/static/images/img02.jpg
plonetheme/leavesdew/static/images/img03.jpg
plonetheme/leavesdew/static/images/img04.gif
plonetheme/leavesdew/static/images/img05.jpg